funcshauns/__init__.py
funcshauns/data_validation.py
funcshauns/py.typed
funcshauns/utils.py
funcshauns-0.1.1.7.dist-info/METADATA
funcshauns-0.1.1.7.dist-info/WHEEL
funcshauns-0.1.1.7.dist-info/licenses/LICENSE
funcshauns-0.1.1.7.dist-info/RECORD
